Metadata-Version: 1.0
Name: svj-jobs-toolkit
Version: 0.2
Summary: Description text
Home-page: https://github.com/tklijnsma/svj_jobs_toolkit.git
Author: Thomas Klijnsma
Author-email: tklijnsm@gmail.com
License: BSD 3-Clause License
Platform: UNKNOWN
